exergenics_etl/__init__.py
exergenics_etl/src/__init__.py
exergenics_etl/src/exergenics_etl.py
exergenics_etl/src/logger.py
exergenics_etl/test/__init__.py
exergenics_etl/test/conftest.py
exergenics_etl/test/test_exergenics_etl.py
exergenics_etl/test/test_logger.py
exergenics_etl-1.18.0.dist-info/LICENSE
exergenics_etl-1.18.0.dist-info/METADATA
exergenics_etl-1.18.0.dist-info/WHEEL
exergenics_etl-1.18.0.dist-info/top_level.txt
exergenics_etl-1.18.0.dist-info/RECORD
