Metadata-Version: 2.1
Name: exergenics-etl
Version: 1.18.0
Summary: Exergenics shared Data ETL functions
Home-page: 
Author: Nobel Wong
Author-email: nobel.wong@exergenics.com
License: MIT
Classifier: License :: OSI Approved :: MIT License
Classifier: Programming Language :: Python :: 3.8
Classifier: Operating System :: OS Independent
Requires-Python: >=3.8.10
License-File: LICENSE
Requires-Dist: exergenics>=2.0.0
Requires-Dist: DateTime==5.1
Requires-Dist: pandas>=1.4.0
Requires-Dist: PyMySQL==1.0.2
Requires-Dist: pytz==2022.7.1
Requires-Dist: SQLAlchemy==1.4.46
Requires-Dist: python-dotenv==1.0.0
Requires-Dist: openpyxl==3.0.10
Requires-Dist: Levenshtein==0.21.0
Requires-Dist: regex==2022.10.31
Requires-Dist: dateparser==1.1.5
Requires-Dist: zipp==3.15.0
Requires-Dist: sklearn==0.0
Requires-Dist: plotly==5.4.0
Requires-Dist: eng==0.1.1
Provides-Extra: dev
Requires-Dist: pytest>=7.0; extra == "dev"
Requires-Dist: twine>=4.0.2; extra == "dev"
Requires-Dist: bump==1.3.2; extra == "dev"
